sls_client/__init__.py
sls_client/constants.py
sls_client/domain_search.py
sls_client/elastic_client.py
sls_client/find_host_info.py
sls_client/find_ma.py
sls_client/host_analysis.py
sls_client/latency_query.py
sls_client/query.py
sls_client/records.py
sls_client/text_search.py
sls_client/validators.py
sls_client-2.0.4.data/scripts/find_ps_ma
sls_client-2.0.4.data/scripts/sls_cache_report
sls_client-2.0.4.data/scripts/sls_dig
sls_client-2.0.4.data/scripts/sls_report
sls_client-2.0.4.data/scripts/sls_text_search
sls_client-2.0.4.dist-info/LICENSE
sls_client-2.0.4.dist-info/METADATA
sls_client-2.0.4.dist-info/WHEEL
sls_client-2.0.4.dist-info/top_level.txt
sls_client-2.0.4.dist-info/RECORD
